{
  "type": "record",
  "name": "SpatialProps",
  "namespace": null,
  "fields": [
    {
      "type": "Vec2f64",
      "name": "position",
      "default": null,
      "doc": null,
      "aliases": []
    },
    {
      "type": "double",
      "name": "rotation_rad",
      "default": null,
      "doc": null,
      "aliases": []
    },
    {
      "type": "double",
      "name": "radius",
      "default": null,
      "doc": null,
      "aliases": []
    }
  ],
  "doc": "{\"version\": 1}",
  "aliases": []
}